sanic_adapters/__init__.py
sanic_adapters/adapters.py
sanic_adapters/decorators.py
sanic_adapters/formatters.py
sanic_adapters/resources.py
sanic_adapters/routing.py
sanic_adapters-0.2.2.dist-info/LICENSE
sanic_adapters-0.2.2.dist-info/METADATA
sanic_adapters-0.2.2.dist-info/WHEEL
sanic_adapters-0.2.2.dist-info/RECORD
