Metadata-Version: 2.1
Name: sanic-adapters
Version: 0.2.2
Summary: Set of semi-adapters for Sanic framework to autodiscovery routes defined by adapters @route decorator instead of defining multiple resources or registering each route, resource, and blueprint in separate calls.
License: BSD 3-Clause License
Author: Michał Ligus
Author-email: maveilthain@gmail.com
Requires-Python: >=3.12,<4.0
Classifier: License :: Other/Proprietary License
Classifier: Programming Language :: Python :: 3
Classifier: Programming Language :: Python :: 3.12
Classifier: Programming Language :: Python :: 3.13
Requires-Dist: dependency-injector[yaml] (>=4.45.0,<5.0.0)
Requires-Dist: sanic[ext] (>=24.12.0,<25.0.0)
Project-URL: Homepage, https://github.com/pytheons/sanic-adapters
